mkdocs_tamerdocs-0.0.3.dist-info/DESCRIPTION.rst
mkdocs_tamerdocs-0.0.3.dist-info/METADATA
mkdocs_tamerdocs-0.0.3.dist-info/RECORD
mkdocs_tamerdocs-0.0.3.dist-info/WHEEL
mkdocs_tamerdocs-0.0.3.dist-info/entry_points.txt
mkdocs_tamerdocs-0.0.3.dist-info/metadata.json
mkdocs_tamerdocs-0.0.3.dist-info/top_level.txt
site/__init__.py
tamerdocs/404.html
tamerdocs/__init__.py
tamerdocs/base.html
tamerdocs/content.html
tamerdocs/main.html
tamerdocs/nav-sub.html
tamerdocs/nav.html
tamerdocs/toc.html
tamerdocs/css/asciinema-player.css
tamerdocs/css/base.css
tamerdocs/css/bootstrap-custom.min.css
tamerdocs/css/font-awesome-4.5.0.css
tamerdocs/css/highlight.css
tamerdocs/css/mindmap.css
tamerdocs/fonts/fontawesome-webfont.eot
tamerdocs/fonts/fontawesome-webfont.svg
tamerdocs/fonts/fontawesome-webfont.ttf
tamerdocs/fonts/fontawesome-webfont.woff
tamerdocs/fonts/glyphicons-halflings-regular.eot
tamerdocs/fonts/glyphicons-halflings-regular.svg
tamerdocs/fonts/glyphicons-halflings-regular.ttf
tamerdocs/fonts/glyphicons-halflings-regular.woff
tamerdocs/fonts/LigatureSymbols/LigatureSymbols-2.11.eot
tamerdocs/fonts/LigatureSymbols/LigatureSymbols-2.11.svg
tamerdocs/fonts/LigatureSymbols/LigatureSymbols-2.11.ttf
tamerdocs/fonts/LigatureSymbols/LigatureSymbols-2.11.woff
tamerdocs/fonts/LigatureSymbols/style.css
tamerdocs/img/favicon.ico
tamerdocs/img/grid.png
tamerdocs/js/asciinema-player.js
tamerdocs/js/base.js
tamerdocs/js/bootstrap-3.0.3.min.js
tamerdocs/js/highlight.pack.js
tamerdocs/js/jquery-1.10.2.min.js
tamerdocs/js/jquery-1.12.3.min.js
