Metadata-Version: 2.0
Name: mkdocs-tamerdocs
Version: 0.0.3
Summary: Mkdocs theme used on AndroidTamer Documentation portals
Home-page: https://anantshri.github.io/mkdocs-tamerdocs/
Author: Anant Shrivastava
Author-email: anant@anantshri.info
License: GPL
Keywords: mkdocs,documentation,theme
Platform: UNKNOWN
